{
  "en": {
    "page": {
      "title": "Add or change steps - {{ applicationName }}",
      "errorTitle": "Error: Add or change steps - {{ applicationName }}"
    },
    "mainHeading": {
      "title": "Add or change steps to {{ subject.possessiveName }} goal",
      "caption": "{{ goal.title }}"
    },
    "step": {
      "description": {
        "label": "What should they do to achieve the goal?",
        "hint": "Enter one step at a time.",
        "autocompleteHint": "Select a suggested step or enter your own."
      },
      "actor": {
        "label": "Who will do the step?",
        "hint": "Add one person or agency.",
        "options": [
          "Choose someone",
          "{{ subject.givenName }}",
          "Probation practitioner",
          "Programme staff",
          "Partnership agency",
          "Commissioned rehabilitative services (CRS) provider",
          "Someone else (include who in the step)"
        ]
      }
    },
    "saveButtonText": "Save and continue",
    "addAnotherButton": "Add another step",
    "removeStepLinkButton": "Remove",
    "clearStepLinkButton": "Clear",
    "errors": {
      "stepDescription": {
        "isNotEmpty": "Enter what they should do to achieve the goal",
        "maxLength": "What they should do to achieve the goal must be 4,000 characters or less"
      },
      "stepActor": {
        "notContains": "Select who will do the step"
      }
    }
  }
}
